modcam.cpython-39-x86_64-linux-gnu.so
modcam/__init__.pyi
modcam/py.typed
modcam-2026.1.4.dist-info/METADATA
modcam-2026.1.4.dist-info/WHEEL
modcam-2026.1.4.dist-info/RECORD
modcam-2026.1.4.dist-info/licenses/LICENSE
