Metadata-Version: 2.1
Name: modcam
Version: 2026.1.4
Summary: Free and open source software for Computer Aided Manufacturing (CAM) research
Classifier: License :: OSI Approved :: Mozilla Public License 2.0 (MPL 2.0)
Classifier: Intended Audience :: Science/Research
Classifier: Intended Audience :: Manufacturing
Classifier: Topic :: Scientific/Engineering
Project-URL: homepage, https://github.com/modCAM/modcam-python
Requires-Python: >=3.9
Requires-Dist: numpy
